[
  {
    "name": "Республика Саха (Якутия), арктика",
    "settlements": [
      {
        "label": "200",
        "settlements": 17,
        "population": 1796
      },
      {
        "label": "500",
        "settlements": 35,
        "population": 12210
      },
      {
        "label": "1000",
        "settlements": 15,
        "population": 9827
      },
      {
        "label": "more1000",
        "settlements": 17,
        "population": 40653
      }
    ],
    "fuel": [
      {
        "label": "уголь",
        "data": 124.1
      },
      {
        "label": "дрова",
        "data": 0
      },
      {
        "label": "газ",
        "data": 0
      },
      {
        "label": "нефть",
        "data": 72.5
      },
      {
        "label": "ГКТ",
        "data": 18.1
      },
      {
        "label": "дизель",
        "data": 85.6
      },
      {
        "label": "бензин",
        "data": 0
      }
    ]
  },
  {
    "name": "Республика Саха (Якутия), юг",
    "settlements": [
      {
        "label": "200",
        "settlements": 20,
        "population": 2368
      },
      {
        "label": "500",
        "settlements": 23,
        "population": 7957
      },
      {
        "label": "1000",
        "settlements": 11,
        "population": 7701
      },
      {
        "label": "more1000",
        "settlements": 5,
        "population": 9237
      }
    ],
    "fuel": [
      {
        "label": "уголь",
        "data": 60.6
      },
      {
        "label": "дрова",
        "data": 0.1
      },
      {
        "label": "газ",
        "data": 2.6
      },
      {
        "label": "нефть",
        "data": 2.5
      },
      {
        "label": "ГКТ",
        "data": 2.8
      },
      {
        "label": "дизель",
        "data": 19.3
      },
      {
        "label": "бензин",
        "data": 0
      }
    ]
  },
  {
    "name": "Забайкальский край",
    "settlements": [
      {
        "label": "200",
        "settlements": 16,
        "population": 1088
      },
      {
        "label": "500",
        "settlements": 5,
        "population": 1383
      },
      {
        "label": "1000",
        "settlements": 2,
        "population": 1765
      },
      {
        "label": "more1000",
        "settlements": 0,
        "population": 0
      }
    ],
    "fuel": [
      {
        "label": "уголь",
        "data": 1.4
      },
      {
        "label": "дрова",
        "data": 0.8
      },
      {
        "label": "газ",
        "data": 0
      },
      {
        "label": "нефть",
        "data": 0
      },
      {
        "label": "ГКТ",
        "data": 0
      },
      {
        "label": "дизель",
        "data": 1.8
      },
      {
        "label": "бензин",
        "data": 0
      }
    ]
  },
  {
    "name": "Камчатский край",
    "settlements": [
      {
        "label": "200",
        "settlements": 12,
        "population": 952
      },
      {
        "label": "500",
        "settlements": 13,
        "population": 4298
      },
      {
        "label": "1000",
        "settlements": 9,
        "population": 6104
      },
      {
        "label": "more1000",
        "settlements": 9,
        "population": 20744
      }
    ],
    "fuel": [
      {
        "label": "уголь",
        "data": 0
      },
      {
        "label": "дрова",
        "data": 0
      },
      {
        "label": "газ",
        "data": 2.3
      },
      {
        "label": "нефть",
        "data": 0
      },
      {
        "label": "ГКТ",
        "data": 0
      },
      {
        "label": "дизель",
        "data": 25.9
      },
      {
        "label": "бензин",
        "data": 0
      }
    ]
  },
  {
    "name": "Приморский край",
    "settlements": [
      {
        "label": "200",
        "settlements": 16,
        "population": 1823
      },
      {
        "label": "500",
        "settlements": 3,
        "population": 1223
      },
      {
        "label": "1000",
        "settlements": 2,
        "population": 1610
      },
      {
        "label": "more1000",
        "settlements": 1,
        "population": 2933
      }
    ],
    "fuel": [
      {
        "label": "уголь",
        "data": 0.1
      },
      {
        "label": "дрова",
        "data": 1.1
      },
      {
        "label": "газ",
        "data": 0
      },
      {
        "label": "нефть",
        "data": 0
      },
      {
        "label": "ГКТ",
        "data": 0
      },
      {
        "label": "дизель",
        "data": 7.8
      },
      {
        "label": "бензин",
        "data": 0
      }
    ]
  },
  {
    "name": "Хабаровский край",
    "settlements": [
      {
        "label": "200",
        "settlements": 48,
        "population": 3630
      },
      {
        "label": "500",
        "settlements": 31,
        "population": 10091
      },
      {
        "label": "1000",
        "settlements": 15,
        "population": 10302
      },
      {
        "label": "more1000",
        "settlements": 10,
        "population": 19517
      }
    ],
    "fuel": [
      {
        "label": "уголь",
        "data": 80.2
      },
      {
        "label": "дрова",
        "data": 8.8
      },
      {
        "label": "газ",
        "data": 7.8
      },
      {
        "label": "нефть",
        "data": 0
      },
      {
        "label": "ГКТ",
        "data": 0
      },
      {
        "label": "дизель",
        "data": 82.6
      },
      {
        "label": "бензин",
        "data": 0
      }
    ]
  },
  {
    "name": "Магаданская область",
    "settlements": [
      {
        "label": "200",
        "settlements": 7,
        "population": 494
      },
      {
        "label": "500",
        "settlements": 2,
        "population": 565
      },
      {
        "label": "1000",
        "settlements": 0,
        "population": 0
      },
      {
        "label": "more1000",
        "settlements": 1,
        "population": 1300
      }
    ],
    "fuel": [
      {
        "label": "уголь",
        "data": 0
      },
      {
        "label": "дрова",
        "data": 0
      },
      {
        "label": "газ",
        "data": 0
      },
      {
        "label": "нефть",
        "data": 0
      },
      {
        "label": "ГКТ",
        "data": 0
      },
      {
        "label": "дизель",
        "data": 5.3
      },
      {
        "label": "бензин",
        "data": 0
      }
    ]
  },
  {
    "name": "Чукотский автономный округ",
    "settlements": [
      {
        "label": "200",
        "settlements": 9,
        "population": 1158
      },
      {
        "label": "500",
        "settlements": 15,
        "population": 4822
      },
      {
        "label": "1000",
        "settlements": 7,
        "population": 4559
      },
      {
        "label": "more1000",
        "settlements": 4,
        "population": 6090
      }
    ],
    "fuel": [
      {
        "label": "уголь",
        "data": 68.1
      },
      {
        "label": "дрова",
        "data": 0
      },
      {
        "label": "газ",
        "data": 0
      },
      {
        "label": "нефть",
        "data": 0
      },
      {
        "label": "ГКТ",
        "data": 0
      },
      {
        "label": "дизель",
        "data": 33.9
      },
      {
        "label": "бензин",
        "data": 0
      }
    ]
  },
  {
    "name": "Сахалинская область, Курилы",
    "settlements": [
      {
        "label": "200",
        "settlements": 11,
        "population": 717
      },
      {
        "label": "500",
        "settlements": 3,
        "population": 1335
      },
      {
        "label": "1000",
        "settlements": 4,
        "population": 2702
      },
      {
        "label": "more1000",
        "settlements": 1,
        "population": 17747
      }
    ],
    "fuel": [
      {
        "label": "уголь",
        "data": 1.5
      },
      {
        "label": "дрова",
        "data": 0.1
      },
      {
        "label": "газ",
        "data": 0.9
      },
      {
        "label": "нефть",
        "data": 0
      },
      {
        "label": "ГКТ",
        "data": 0
      },
      {
        "label": "дизель",
        "data": 3.2
      },
      {
        "label": "бензин",
        "data": 0.04
      }
    ]
  },
  {
    "name": "Амурская область",
    "settlements": [
      {
        "label": "200",
        "settlements": 4,
        "population": 256
      },
      {
        "label": "500",
        "settlements": 1,
        "population": 316
      },
      {
        "label": "1000",
        "settlements": 0,
        "population": 0
      },
      {
        "label": "more1000",
        "settlements": 0,
        "population": 0
      }
    ],
    "fuel": [
      {
        "label": "уголь",
        "data": 10.3
      },
      {
        "label": "дрова",
        "data": 0
      },
      {
        "label": "газ",
        "data": 0
      },
      {
        "label": "нефть",
        "data": 0
      },
      {
        "label": "ГКТ",
        "data": 0
      },
      {
        "label": "дизель",
        "data": 44.1
      },
      {
        "label": "бензин",
        "data": 0
      }
    ]
  }
]
